asd_feeder/__init__.py
asd_feeder/__main__.py
asd_feeder/asd_controls.py
asd_feeder/asd_watchdog.py
asd_feeder/command_interpreter.py
asd_feeder/logger.py
asd_feeder/spec_compy_controller.py
asd_feeder/spectralon_corrector.py
asd_feeder/utils.py
asd_feeder/img2/exit.png
asd_feeder/img2/optimizing.png
asd_feeder/img2/rs3adjustconfig.png
asd_feeder/img2/rs3adjustconfig2.png
asd_feeder/img2/rs3control.png
asd_feeder/img2/rs3control2.png
asd_feeder/img2/rs3display.png
asd_feeder/img2/rs3displaygray.png
asd_feeder/img2/rs3instrumentcontrol.png
asd_feeder/img2/rs3instrumentcontrol2.png
asd_feeder/img2/rs3menu.png
asd_feeder/img2/rs3ok.png
asd_feeder/img2/rs3ok2.png
asd_feeder/img2/rs3specsave.png
asd_feeder/img2/rs3specsave2.png
asd_feeder/img2/status_color.png
asd_feeder/img2/white_status.png
asd_feeder/spectralon_data/spec_correction_i0.csv
asd_feeder/spectralon_data/spec_correction_i0_405nm.csv
asd_feeder/spectralon_data/spec_correction_i0_off_plane.csv
asd_feeder/spectralon_data/spec_correction_i30.csv
asd_feeder/spectralon_data/spec_correction_i45.csv
asd_feeder/spectralon_data/spec_correction_i60.csv
asd_feeder/spectralon_data/spec_correction_i60_405nm.csv
asd_feeder/spectralon_data/spec_correction_i60_off_plane.csv
asd_feeder/spectralon_data/spectralon.csv
asd_feeder/startup/start_asd_feeder.cmd
asd_feeder/startup/start_asd_watchdog.cmd
pi_feeder/__init__.py
pi_feeder/encoder.py
pi_feeder/encodertester.py
pi_feeder/goniometer.py
pi_feeder/gpioreader.py
pi_feeder/limit_switch.py
pi_feeder/limit_switch_tester.py
pi_feeder/motor.py
pi_feeder/motorpulser.py
pi_feeder/pi_controller.py
tanager_data_io/__init__.py
tanager_data_io/data_io.py
tanager_feeder/__init__.py
tanager_feeder/__main__.py
tanager_feeder/remote_directory_worker.py
tanager_feeder/utils.py
tanager_feeder/verticalscrolledframe.py
tanager_feeder/command_handlers/__init__.py
tanager_feeder/command_handlers/calfile_config_handler.py
tanager_feeder/command_handlers/check_writeable_handler.py
tanager_feeder-1.10.dist-info/licenses/LICENSE
tanager_feeder-1.10.dist-info/METADATA
tanager_feeder-1.10.dist-info/WHEEL
tanager_feeder-1.10.dist-info/entry_points.txt
tanager_feeder-1.10.dist-info/top_level.txt
tanager_feeder-1.10.dist-info/RECORD
