Metadata-Version: 2.4
Name: tanager-feeder
Version: 1.10
Summary: Control software for spectroscopy using ASD RS3 and ViewSpec Pro
Home-page: https://github.com/westernmarslab/tanager-feeder
Author: Kathleen Hoza
Author-email: kathleenhoza@gmail.com
License: Creative Commons Attribution-Noncommercial-Share Alike license
Requires-Python: >=3
License-File: LICENSE
Requires-Dist: pywinauto
Requires-Dist: pyautogui
Requires-Dist: tanager_tcp
Requires-Dist: numpy
Requires-Dist: matplotlib
Requires-Dist: colorutils
Requires-Dist: cython
Requires-Dist: numpy
Requires-Dist: playsound
Requires-Dist: psutil
Requires-Dist: pygame<1.9.7,>=1.9.5
Requires-Dist: tanager-tcp
Dynamic: author
Dynamic: author-email
Dynamic: home-page
Dynamic: license
Dynamic: license-file
Dynamic: requires-dist
Dynamic: requires-python
Dynamic: summary
